{
  "1": [
    "ahu",
    "a"
  ],
  "2": [
    "ahu",
    "a"
  ],
  "3": [
    "ahu",
    "a"
  ],
  "4": [
    "ahu",
    "a"
  ],
  "5": [
    "ahu",
    "a"
  ],
  "7": [
    "energy",
    "meter",
    "building",
    "bld",
    "kwh"
  ],
  "8": [
    "flow",
    "sensor",
    "f",
    "vav",
    "av"
  ],
  "9": [
    "flow",
    "sensor",
    "f",
    "vav",
    "mn"
  ],
  "10": [
    "flow",
    "sensor",
    "f",
    "vav",
    "mx"
  ],
  "11": [
    "flow",
    "sensor",
    "f",
    "vav",
    "av"
  ],
  "12": [
    "flow",
    "sensor",
    "f",
    "vav",
    "mn"
  ],
  "13": [
    "flow",
    "sensor",
    "f",
    "vav",
    "mx"
  ],
  "14": [
    "flow",
    "sensor",
    "f",
    "vav",
    "av"
  ],
  "15": [
    "flow",
    "sensor",
    "f",
    "vav",
    "mn"
  ],
  "16": [
    "flow",
    "sensor",
    "f",
    "vav",
    "mx"
  ],
  "17": [
    "flow",
    "sensor",
    "f",
    "vav",
    "av"
  ],
  "18": [
    "flow",
    "sensor",
    "f",
    "vav",
    "mn"
  ],
  "19": [
    "flow",
    "sensor",
    "f",
    "vav",
    "mx"
  ],
  "20": [
    "flow",
    "sensor",
    "f",
    "vav",
    "av"
  ]
}